Metadata-Version: 1.0
Name: basicmatrix
Version: 0.1
Summary: Basic matrix arithmetic
Home-page: UNKNOWN
Author: Christiaan van Eeden
Author-email: christiaanveeden@gmail.com
License: UNKNOWN
Platform: UNKNOWN
